{
  "schema_version": 1,
  "default_review_profile": "standard",
  "profiles": {
    "light": {
      "max_allowed": {
        "p0": 0,
        "p1": 0,
        "p2": 5,
        "p3": 10
      },
      "required_checks": [
        "scope",
        "verify"
      ]
    },
    "standard": {
      "max_allowed": {
        "p0": 0,
        "p1": 0,
        "p2": 3,
        "p3": 8
      },
      "required_checks": [
        "scope",
        "verify",
        "review"
      ]
    },
    "strict": {
      "max_allowed": {
        "p0": 0,
        "p1": 0,
        "p2": 0,
        "p3": 3
      },
      "required_checks": [
        "scope",
        "verify",
        "review",
        "ready-validation"
      ]
    }
  }
}
